Metadata-Version: 2.1
Name: django-rest-auth-e2e
Version: 0.9.6
Summary: Create a set of REST API endpoints for Authentication and Registration
Home-page: https://github.com/Roniee007/django-rest-auth-e2e
Author: rounak kabra
Author-email: rounak.kabra@e2enetworks.com
Keywords: django rest auth registration rest-framework django-registration api
Classifier: Framework :: Django
Classifier: Intended Audience :: Developers
Classifier: Intended Audience :: System Administrators
Classifier: Operating System :: OS Independent
Classifier: Topic :: Software Development
Provides-Extra: with_social
License-File: LICENSE
